odoo/addons/l10n_es_vat_prorate/README.rst
odoo/addons/l10n_es_vat_prorate/__init__.py
odoo/addons/l10n_es_vat_prorate/__manifest__.py
odoo/addons/l10n_es_vat_prorate/data/account_template_tax.xml
odoo/addons/l10n_es_vat_prorate/i18n/es.po
odoo/addons/l10n_es_vat_prorate/i18n/l10n_es_vat_prorate.pot
odoo/addons/l10n_es_vat_prorate/models/__init__.py
odoo/addons/l10n_es_vat_prorate/models/account_move.py
odoo/addons/l10n_es_vat_prorate/models/account_tax.py
odoo/addons/l10n_es_vat_prorate/models/res_company.py
odoo/addons/l10n_es_vat_prorate/readme/CONFIGURE.rst
odoo/addons/l10n_es_vat_prorate/readme/CONTRIBUTORS.rst
odoo/addons/l10n_es_vat_prorate/readme/DESCRIPTION.rst
odoo/addons/l10n_es_vat_prorate/security/ir.model.access.csv
odoo/addons/l10n_es_vat_prorate/static/description/icon.png
odoo/addons/l10n_es_vat_prorate/static/description/index.html
odoo/addons/l10n_es_vat_prorate/tests/__init__.py
odoo/addons/l10n_es_vat_prorate/tests/test_prorate_sii.py
odoo/addons/l10n_es_vat_prorate/tests/test_vat_prorate.py
odoo/addons/l10n_es_vat_prorate/tests/json/sii_in_invoice_p_iva0_ns_p_iva10_bc_dict.json
odoo/addons/l10n_es_vat_prorate/tests/json/sii_in_invoice_p_iva10_bc_dict.json
odoo/addons/l10n_es_vat_prorate/tests/json/sii_in_invoice_p_iva10_bc_p_irpf19_p_iva21_sc_p_irpf19_dict.json
odoo/addons/l10n_es_vat_prorate/tests/json/sii_in_invoice_p_iva10_bc_p_irpf1_dict.json
odoo/addons/l10n_es_vat_prorate/tests/json/sii_in_invoice_p_iva10_bc_p_req014_p_iva21_sc_p_req52_dict.json
odoo/addons/l10n_es_vat_prorate/tests/json/sii_in_invoice_p_iva21_sp_ex_dict.json
odoo/addons/l10n_es_vat_prorate/tests/json/sii_in_refund_p_iva10_bc_dict.json
odoo/addons/l10n_es_vat_prorate/tests/json/sii_in_refund_p_iva21_sp_in_dict.json
odoo/addons/l10n_es_vat_prorate/tests/json/sii_out_invoice_s_iva0_sp_i_s_iva0_ic_dict.json
odoo/addons/l10n_es_vat_prorate/tests/json/sii_out_invoice_s_iva10b_dict.json
odoo/addons/l10n_es_vat_prorate/tests/json/sii_out_invoice_s_iva10b_s_irpf1_dict.json
odoo14_addon_l10n_es_vat_prorate-14.0.2.1.0.dist-info/METADATA
odoo14_addon_l10n_es_vat_prorate-14.0.2.1.0.dist-info/WHEEL
odoo14_addon_l10n_es_vat_prorate-14.0.2.1.0.dist-info/top_level.txt
odoo14_addon_l10n_es_vat_prorate-14.0.2.1.0.dist-info/RECORD
